setup.py
distributions/Binomialdistribution.py
distributions/Gaussiandistribution.py
distributions/Generaldistribution.py
distributions/__init__.py
seanblack_udacity_distributions_example.egg-info/PKG-INFO
seanblack_udacity_distributions_example.egg-info/SOURCES.txt
seanblack_udacity_distributions_example.egg-info/dependency_links.txt
seanblack_udacity_distributions_example.egg-info/not-zip-safe
seanblack_udacity_distributions_example.egg-info/top_level.txt