Metadata-Version: 1.0
Name: seanblack-udacity-distributions-example
Version: 0.1
Summary: Gaussian and Binomial distributions
Home-page: UNKNOWN
Author: Sean Black
Author-email: skblackx2@gmail.com
License: UNKNOWN
Platform: UNKNOWN
